Exp4/design.sv
module stack_behavioural ( 
input clk,                
input rstN,               
// Clock signal 
// Active-low reset signal 
input [3:0] data_in,      
input push,               
input pop,                
// Data input for push operation 
// Push operation signal 
// Pop operation signal 
output reg [3:0] data_out, // Data output for pop operation 
output reg full,          
output reg empty          
); 
// Flag indicating if the stack is full 
// Flag indicating if the stack is empty 
// Define an 8-depth stack memory with 4-bit wide data 
reg [3:0] stack_mem [7:0];
// Stack pointer to keep track of the stack position, points to the last free index in memory 
reg [3:0] stack_pointer; 
 
// Integer variable for loop indexing 
integer i; 
 
// Always block triggered on the positive edge of the clock 
always @(posedge clk) begin 
    if (!rstN) begin   // If reset signal is active (low) 
        // Initialize the stack memory to zero 
        for (i = 0; i < 8; i = i + 1) begin 
            stack_mem[i] <= 0; 
        end 
        // Reset the stack pointer to zero 
        stack_pointer <= 0; 
        // Set the full flag to 0 (stack is not full) 
        full <= 0; 
        // Set the empty flag to 1 (stack is empty) 
        empty <= 1; 
    end else begin 
        // If push signal is active, pop signal is not active, and stack is not full 
        if (push && !pop && !full) begin 
            // Push the data into the stack memory at the current stack pointer position 
            stack_mem[stack_pointer] <= data_in; 
            // Increment the stack pointer 
            stack_pointer <= stack_pointer + 1; 
            // Update the full flag: stack is full if stack pointer is 8 
            full <= (stack_pointer == 8); 
            // Update the empty flag: stack is empty if stack pointer is 0 
            empty <= 0; 
        end  
        // If pop signal is active, push signal is not active, and stack is not empty 
        else if (pop && !push && !empty) begin 
            // Decrement the stack pointer 
            stack_pointer <= stack_pointer - 1; 
            // Pop the data from the stack memory at the new stack pointer position 
            data_out <= stack_mem[stack_pointer]; 
            // Update the full flag: stack is full if stack pointer is 8 
            full <= 0; 
            // Update the empty flag: stack is empty if stack pointer is 0 
            empty <= (stack_pointer == 0); 
        end 
    end 
end 
 
endmodule

Exp4/testbench.sv
module testbench; 
 
  // Declare testbench signals 
  reg clk;                // Clock signal 
  reg rstN;               // Reset signal (active low) 
  reg [3:0] data_in;      // 4-bit data input 
  reg push;               // Push control signal 
  reg pop;                // Pop control signal 
   
  // Output signals from the stack module 
  wire [3:0] data_out;    // 4-bit data output 
  wire full;              // Full flag 
  wire empty;             // Empty flag 
   
  // Clock period constant 
  localparam CLK_PERIOD = 10; 
   
  // Generate clock signal with a period of CLK_PERIOD 
  always #(CLK_PERIOD/2) clk = ~clk;
// Instantiate the stack_behavioural module 
stack_behavioural sb ( 
.clk(clk),  
.rstN(rstN),  
.data_in(data_in),  
.push(push),  
.pop(pop),  
.data_out(data_out),  
.full(full),  
.empty(empty) 
); 
// Initial block for setup 
initial begin 
clk = 0;           
push = 0;          
pop = 0;           
rstN = 0;          
// Initialize clock signal 
// Initialize push signal 
// Initialize pop signal 
// Initialize reset signal (active low) 
data_in = 4'b0000; // Initialize data input to 0 
$dumpfile("testbench.vcd"); // Specify VCD file for waveform dump 
$dumpvars(0, testbench);    // Dump all variables in the testbench module 
end 
// Initial block for test sequence 
initial begin 
rstN = 0; // Assert reset signal to reset the stack 
#(CLK_PERIOD*2); // Wait for 2 clock cycles 
 rstN = 1; // Deassert reset signal to start normal operation 
pop = 1; // Attempt to pop from empty stack 
#(CLK_PERIOD*3); // Wait for 3 clock cycles 
pop = 0; // Deassert pop signal 
push = 1; // Assert push signal 
data_in = 4'b1101; // Load 13 into data input 
#(CLK_PERIOD*1); // Wait for 1 clock cycle 
data_in = 4'b1111; // Load 15 into data input 
#(CLK_PERIOD*1); // Wait for 1 clock cycle 
data_in = 4'b0010; // Load 2 into data input 
#(CLK_PERIOD*1); // Wait for 1 clock cycle 
data_in = 4'b1001; // Load 9 into data input 
#(CLK_PERIOD*1); // Wait for 1 clock cycle 
push = 0; // Deassert push signal 
pop = 1; // Assert pop signal 
#(CLK_PERIOD*1); // Wait for 1 clock cycle 
push = 1; // Assert push signal 
pop = 0; // Deassert pop signal 
data_in = 4'b0011; // Load 3 into data input
    #(CLK_PERIOD*1); // Wait for 1 clock cycle 
    data_in = 4'b1001; // Load 9 into data input 
     
    #(CLK_PERIOD*1); // Wait for 1 clock cycle 
    push = 0; // Deassert push signal 
    pop = 1; // Assert pop signal 
     
    #(CLK_PERIOD*8.5); // Wait for 8.5 clock cycles 
    $finish; // End simulation 
  end 
 
endmodule

Exp4/testbench.vcd
$date
Sun Jul 14 02:23:43 2024
$end
$version
Riviera-PRO Version 2023.04.112.8911
$end
$timescale
1 ns
$end

$scope module testbench $end
$var wire 4 ! data_out [3:0] $end
$var wire 1 " full $end
$var wire 1 # empty $end
$var reg 1 $ clk $end
$var reg 1 % rstN $end
$var reg 4 & data_in [3:0] $end
$var reg 1 ' push $end
$var reg 1 ( pop $end
$var parameter 32 ) CLK_PERIOD [31:0] $end

$scope module sb $end
$var wire 1 * clk $end
$var wire 1 + rstN $end
$var wire 4 , data_in [3:0] $end
$var wire 1 - push $end
$var wire 1 . pop $end
$var reg 4 / data_out [3:0] $end
$var reg 1 0 full $end
$var reg 1 1 empty $end
$var reg 4 2 stack_pointer [3:0] $end
$var integer 32 3 i $end
$upscope $end

$upscope $end

$enddefinitions $end
$dumpvars
bx !
x"
x#
0$
0%
b0 &
0'
0(
b1010 )
0*
0+
b0 ,
0-
0.
bx /
x0
x1
bx 2
bx 3
$end
#5
1$
1*
b1000 3
b0 2
00
11
1#
0"
#10
0$
0*
#15
1$
1*
#20
1%
1(
0$
0*
1.
1+
#25
1$
1*
#30
0$
0*
#35
1$
1*
#40
0$
0*
#45
1$
1*
#50
0(
1'
b1101 &
0$
0*
b1101 ,
1-
0.
#55
1$
1*
b1 2
01
0#
#60
b1111 &
0$
0*
b1111 ,
#65
1$
1*
b10 2
#70
b10 &
0$
0*
b10 ,
#75
1$
1*
b11 2
#80
b1001 &
0$
0*
b1001 ,
#85
1$
1*
b100 2
#90
0'
1(
0$
0*
1.
0-
#95
1$
1*
b11 2
b0 /
b0 !
#100
1'
0(
b11 &
0$
0*
b11 ,
0.
1-
#105
1$
1*
b100 2
#110
b1001 &
0$
0*
b1001 ,
#115
1$
1*
b101 2
#120
0'
1(
0$
0*
1.
0-
#125
1$
1*
b100 2
#130
0$
0*
#135
1$
1*
b11 2
b1001 /
b1001 !
#140
0$
0*
#145
1$
1*
b10 2
b11 /
b11 !
#150
0$
0*
#155
1$
1*
b1 2
b10 /
b10 !
#160
0$
0*
#165
1$
1*
b0 2
b1111 /
b1111 !
#170
0$
0*
#175
1$
1*
b1111 2
b1101 /
11
1#
b1101 !
